{
  "visState": "{\"title\":\"OSSEC Alerts - Process and PID\",\"type\":\"pie\",\"params\":{\"addTooltip\":true,\"addLegend\":true,\"legendPosition\":\"right\",\"isDonut\":false},\"aggs\":[{\"id\":\"1\",\"enabled\":true,\"type\":\"count\",\"schema\":\"metric\",\"params\":{}},{\"id\":\"2\",\"enabled\":true,\"type\":\"terms\",\"schema\":\"segment\",\"params\":{\"field\":\"process.keyword\",\"size\":5,\"order\":\"desc\",\"orderBy\":\"1\"}},{\"id\":\"3\",\"enabled\":true,\"type\":\"terms\",\"schema\":\"segment\",\"params\":{\"field\":\"pid.keyword\",\"size\":5,\"order\":\"desc\",\"orderBy\":\"1\"}}],\"listeners\":{}}", 
  "description": "", 
  "title": "OSSEC Alerts - Process and PID", 
  "uiStateJSON": "{}", 
  "version": 1, 
  "savedSearchId": "d9096bb0-342f-11e7-9e93-53b62e1857b2", 
  "kibanaSavedObjectMeta": {
    "searchSourceJSON": "{\"filter\":[]}"
  }
}